kotlin version: 2.2.10
error message: org.jetbrains.kotlin.codegen.CompilationException: Back-end (JVM) Internal error: Couldn't transform method node:
FameNavGraph (Landroidx/navigation/NavHostController;Lkotlin/jvm/functions/Function0;Lkotlin/jvm/functions/Function1;Lkotlin/jvm/functions/Function0;Lkotlin/jvm/functions/Function0;Landroidx/compose/ui/Modifier;Ljava/lang/String;Landroidx/compose/runtime/Composer;II)V:
  @Landroidx/compose/runtime/Composable;() // invisible
  @Landroidx/compose/runtime/ComposableTarget;(applier="androidx.compose.ui.UiComposable") // invisible
    // annotable parameter count: 10 (visible)
    // annotable parameter count: 10 (invisible)
    @Lorg/jetbrains/annotations/NotNull;() // invisible, parameter 0
    @Lorg/jetbrains/annotations/NotNull;() // invisible, parameter 1
    @Lorg/jetbrains/annotations/NotNull;() // invisible, parameter 2
    @Lorg/jetbrains/annotations/NotNull;() // invisible, parameter 3
    @Lorg/jetbrains/annotations/NotNull;() // invisible, parameter 4
    @Lorg/jetbrains/annotations/Nullable;() // invisible, parameter 5
    @Lorg/jetbrains/annotations/Nullable;() // invisible, parameter 6
    @Lorg/jetbrains/annotations/Nullable;() // invisible, parameter 7
   L0
    ALOAD 0
    LDC "navController"
    INVOKESTATIC kotlin/jvm/internal/Intrinsics.checkNotNullParameter (Ljava/lang/Object;Ljava/lang/String;)V
    ALOAD 1
    LDC "onNewCareer"
    INVOKESTATIC kotlin/jvm/internal/Intrinsics.checkNotNullParameter (Ljava/lang/Object;Ljava/lang/String;)V
    ALOAD 2
    LDC "onContinue"
    INVOKESTATIC kotlin/jvm/internal/Intrinsics.checkNotNullParameter (Ljava/lang/Object;Ljava/lang/String;)V
    ALOAD 3
    LDC "onLoadGame"
    INVOKESTATIC kotlin/jvm/internal/Intrinsics.checkNotNullParameter (Ljava/lang/Object;Ljava/lang/String;)V
    ALOAD 4
    LDC "onSettings"
    INVOKESTATIC kotlin/jvm/internal/Intrinsics.checkNotNullParameter (Ljava/lang/Object;Ljava/lang/String;)V
   L1
    LINENUMBER 54 L1
    ALOAD 7
    LDC -1680905989
    INVOKEINTERFACE androidx/compose/runtime/Composer.startRestartGroup (I)Landroidx/compose/runtime/Composer; (itf)
    ASTORE 7
    ALOAD 7
    LDC "C(FameNavGraph)N(navController,onNewCareer,onContinue,onLoadGame,onSettings,modifier,startDestination)58@2767L10742,54@2640L10869:NavGraph.kt#5oldka"
    INVOKESTATIC androidx/compose/runtime/ComposerKt.sourceInformation (Landroidx/compose/runtime/Composer;Ljava/lang/String;)V
    ILOAD 8
    ISTORE 10
   L2
    ILOAD 8
    BIPUSH 6
    IAND
    IFNE L3
    ILOAD 10
    ALOAD 7
    ALOAD 0
    INVOKEINTERFACE androidx/compose/runtime/Composer.changedInstance (Ljava/lang/Object;)Z (itf)
    IFEQ L4
    ICONST_4
    GOTO L5
   L4
    ICONST_2
   L5
    IOR
    ISTORE 10
   L3
    ILOAD 8
    BIPUSH 48
    IAND
    IFNE L6
    ILOAD 10
    ALOAD 7
    ALOAD 1
    INVOKEINTERFACE androidx/compose/runtime/Composer.changedInstance (Ljava/lang/Object;)Z (itf)
    IFEQ L7
    BIPUSH 32
    GOTO L8
   L7
    BIPUSH 16
   L8
    IOR
    ISTORE 10
   L6
    ILOAD 8
    SIPUSH 384
    IAND
    IFNE L9
    ILOAD 10
    ALOAD 7
    ALOAD 2
    INVOKEINTERFACE androidx/compose/runtime/Composer.changedInstance (Ljava/lang/Object;)Z (itf)
    IFEQ L10
    SIPUSH 256
    GOTO L11
   L10
    SIPUSH 128
   L11
    IOR
    ISTORE 10
   L9
    ILOAD 8
    SIPUSH 3072
    IAND
    IFNE L12
    ILOAD 10
    ALOAD 7
    ALOAD 3
    INVOKEINTERFACE androidx/compose/runtime/Composer.changedInstance (Ljava/lang/Object;)Z (itf)
    IFEQ L13
    SIPUSH 2048
    GOTO L14
   L13
    SIPUSH 1024
   L14
    IOR
    ISTORE 10
   L12
    ILOAD 8
    SIPUSH 24576
    IAND
    IFNE L15
    ILOAD 10
    ALOAD 7
    ALOAD 4
    INVOKEINTERFACE androidx/compose/runtime/Composer.changedInstance (Ljava/lang/Object;)Z (itf)
    IFEQ L16
    SIPUSH 16384
    GOTO L17
   L16
    SIPUSH 8192
   L17
    IOR
    ISTORE 10
   L15
    ILOAD 9
    BIPUSH 32
    IAND
    IFEQ L18
    ILOAD 10
    LDC 196608
    IOR
    ISTORE 10
    GOTO L19
   L18
    ILOAD 8
    LDC 196608
    IAND
    IFNE L19
    ILOAD 10
    ALOAD 7
    ALOAD 5
    INVOKEINTERFACE androidx/compose/runtime/Composer.changed (Ljava/lang/Object;)Z (itf)
    IFEQ L20
    LDC 131072
    GOTO L21
   L20
    LDC 65536
   L21
    IOR
    ISTORE 10
   L19
    ILOAD 8
    LDC 1572864
    IAND
    IFNE L22
    ILOAD 10
    ILOAD 9
    BIPUSH 64
    IAND
    IFNE L23
    ALOAD 7
    ALOAD 6
    INVOKEINTERFACE androidx/compose/runtime/Composer.changed (Ljava/lang/Object;)Z (itf)
    IFEQ L23
    LDC 1048576
    GOTO L24
   L23
    LDC 524288
   L24
    IOR
    ISTORE 10
   L22
    ALOAD 7
    ILOAD 10
    LDC 599187
    IAND
    LDC 599186
    IF_ICMPEQ L25
    ICONST_1
    GOTO L26
   L25
    ICONST_0
   L26
    ILOAD 10
    ICONST_1
    IAND
    INVOKEINTERFACE androidx/compose/runtime/Composer.shouldExecute (ZI)Z (itf)
    IFEQ L27
    ALOAD 7
    INVOKEINTERFACE androidx/compose/runtime/Composer.startDefaults ()V (itf)
    ILOAD 8
    ICONST_1
    IAND
    IFEQ L28
    ALOAD 7
    INVOKEINTERFACE androidx/compose/runtime/Composer.getDefaultsInvalid ()Z (itf)
    IFEQ L29
   L28
    ILOAD 9
    BIPUSH 32
    IAND
    IFEQ L30
   L31
    LINENUMBER 52 L31
    GETSTATIC androidx/compose/ui/Modifier.Companion : Landroidx/compose/ui/Modifier$Companion;
    CHECKCAST androidx/compose/ui/Modifier
    ASTORE 5
   L30
    ILOAD 9
    BIPUSH 64
    IAND
    IFEQ L32
   L33
    LINENUMBER 53 L33
    GETSTATIC com/fameafrica/afm2026/ui/navigation/Screen$Splash.INSTANCE : Lcom/fameafrica/afm2026/ui/navigation/Screen$Splash;
    INVOKEVIRTUAL com/fameafrica/afm2026/ui/navigation/Screen$Splash.getRoute ()Ljava/lang/String;
    ASTORE 6
    ILOAD 10
    LDC -3670017
    IAND
    ISTORE 10
   L32
    GOTO L34
   L29
    LINENUMBER 45 L29
    ALOAD 7
    INVOKEINTERFACE androidx/compose/runtime/Composer.skipToGroupEnd ()V (itf)
    ILOAD 9
    BIPUSH 64
    IAND
    IFEQ L34
    ILOAD 10
    LDC -3670017
    IAND
    ISTORE 10
   L34
    ALOAD 7
    INVOKEINTERFACE androidx/compose/runtime/Composer.endDefaults ()V (itf)
    INVOKESTATIC androidx/compose/runtime/ComposerKt.isTraceInProgress ()Z
    IFEQ L35
    LDC -1680905989
    ILOAD 10
    ICONST_M1
    LDC "afm.ui.navigation.FameNavGraph (NavGraph.kt:53)"
    INVOKESTATIC androidx/compose/runtime/ComposerKt.traceEventStart (IIILjava/lang/String;)V
   L35
    LINENUMBER 56 L35
    ALOAD 0
   L36
    LINENUMBER 57 L36
    ALOAD 6
   L37
    LINENUMBER 58 L37
    ALOAD 5
    ACONST_NULL
    ACONST_NULL
    ACONST_NULL
    ACONST_NULL
    ACONST_NULL
    ACONST_NULL
    ACONST_NULL
    ALOAD 7
    LDC -442928431
    LDC "CC(remember):NavGraph.kt#9igjgp"
   L38
    LINENUMBER 59 L38
    INVOKESTATIC androidx/compose/runtime/ComposerKt.sourceInformationMarkerStart (Landroidx/compose/runtime/Composer;ILjava/lang/String;)V
    ALOAD 7
    ASTORE 12
    ALOAD 7
    ALOAD 0
    INVOKEINTERFACE androidx/compose/runtime/Composer.changedInstance (Ljava/lang/Object;)Z (itf)
    ILOAD 10
    SIPUSH 896
    IAND
    SIPUSH 256
    IF_ICMPNE L39
    ICONST_1
    GOTO L40
   L39
    ICONST_0
   L40
    IOR
    ILOAD 10
    BIPUSH 112
    IAND
    BIPUSH 32
    IF_ICMPNE L41
    ICONST_1
    GOTO L42
   L41
    ICONST_0
   L42
    IOR
    ILOAD 10
    SIPUSH 7168
    IAND
    SIPUSH 2048
    IF_ICMPNE L43
    ICONST_1
    GOTO L44
   L43
    ICONST_0
   L44
    IOR
    ILOAD 10
    LDC 57344
    IAND
    SIPUSH 16384
    IF_ICMPNE L45
    ICONST_1
    GOTO L46
   L45
    ICONST_0
   L46
    IOR
    ISTORE 13
   L47
    ICONST_0
    ISTORE 14
   L48
    LINENUMBER 319 L48
    ALOAD 12
    INVOKEINTERFACE androidx/compose/runtime/Composer.rememberedValue ()Ljava/lang/Object; (itf)
    ASTORE 15
   L49
    ICONST_0
    ISTORE 16
   L50
    LINENUMBER 320 L50
    ILOAD 13
    IFNE L51
    ALOAD 15
    GETSTATIC androidx/compose/runtime/Composer.Companion : Landroidx/compose/runtime/Composer$Companion;
    INVOKEVIRTUAL androidx/compose/runtime/Composer$Companion.getEmpty ()Ljava/lang/Object;
    IF_ACMPNE L52
   L51
    LINENUMBER 321 L51
    ASTORE 28
    ASTORE 27
    ASTORE 26
    ASTORE 25
    ASTORE 24
    ASTORE 23
    ASTORE 22
    ASTORE 21
    ASTORE 20
    ASTORE 19
    ICONST_0
    ISTORE 17
   L53
    LINENUMBER 59 L53
    ALOAD 0
    ALOAD 2
    ALOAD 1
    ALOAD 3
    ALOAD 4
    INVOKEDYNAMIC invoke(Landroidx/navigation/NavHostController;Lkotlin/jvm/functions/Function1;Lkotlin/jvm/functions/Function0;Lkotlin/jvm/functions/Function0;Lkotlin/jvm/functions/Function0;)Lkotlin/jvm/functions/Function1; [
      // handle kind 0x6 : INVOKESTATIC
      java/lang/invoke/LambdaMetafactory.metafactory(Ljava/lang/invoke/MethodHandles$Lookup;Ljava/lang/String;Ljava/lang/invoke/MethodType;Ljava/lang/invoke/MethodType;Ljava/lang/invoke/MethodHandle;Ljava/lang/invoke/MethodType;)Ljava/lang/invoke/CallSite;
      // arguments:
      (Ljava/lang/Object;)Ljava/lang/Object;, 
      // handle kind 0x6 : INVOKESTATIC
      com/fameafrica/afm2026/ui/navigation/NavGraphKt.FameNavGraph$lambda$162$lambda$161(Landroidx/navigation/NavHostController;Lkotlin/jvm/functions/Function1;Lkotlin/jvm/functions/Function0;Lkotlin/jvm/functions/Function0;Lkotlin/jvm/functions/Function0;Landroidx/navigation/NavGraphBuilder;)Lkotlin/Unit;, 
      (Landroidx/navigation/NavGraphBuilder;)Lkotlin/Unit;
    ]
    GOTO L54
   L54
    ASTORE 29
    ALOAD 19
    ALOAD 20
    ALOAD 21
    ALOAD 22
    ALOAD 23
    ALOAD 24
    ALOAD 25
    ALOAD 26
    ALOAD 27
    ALOAD 28
    ALOAD 29
   L55
    LINENUMBER 321 L55
    ASTORE 18
   L56
    LINENUMBER 322 L56
    ALOAD 12
    ALOAD 18
    INVOKEINTERFACE androidx/compose/runtime/Composer.updateRememberedValue (Ljava/lang/Object;)V (itf)
   L57
    LINENUMBER 323 L57
    ALOAD 18
   L58
    GOTO L59
   L52
    LINENUMBER 324 L52
    ALOAD 15
   L59
    LINENUMBER 319 L59
    NOP
   L60
    LINENUMBER 319 L60
    GOTO L61
   L61
    LINENUMBER 59 L61
    CHECKCAST kotlin/jvm/functions/Function1
    ASTORE 11
    ALOAD 7
    INVOKESTATIC androidx/compose/runtime/ComposerKt.sourceInformationMarkerEnd (Landroidx/compose/runtime/Composer;)V
    ALOAD 11
    ALOAD 7
    BIPUSH 14
    ILOAD 10
    IAND
    BIPUSH 112
    ILOAD 10
    BIPUSH 15
    ISHR
    IAND
    IOR
    SIPUSH 896
    ILOAD 10
    BIPUSH 9
    ISHR
    IAND
    IOR
    ICONST_0
    SIPUSH 1016
   L62
    LINENUMBER 55 L62
    INVOKESTATIC androidx/navigation/compose/NavHostKt.NavHost (Landroidx/navigation/NavHostController;Ljava/lang/String;Landroidx/compose/ui/Modifier;Landroidx/compose/ui/Alignment;Ljava/lang/String;Lkotlin/jvm/functions/Function1;Lkotlin/jvm/functions/Function1;Lkotlin/jvm/functions/Function1;Lkotlin/jvm/functions/Function1;Lkotlin/jvm/functions/Function1;Lkotlin/jvm/functions/Function1;Landroidx/compose/runtime/Composer;III)V
    INVOKESTATIC androidx/compose/runtime/ComposerKt.isTraceInProgress ()Z
    IFEQ L63
    INVOKESTATIC androidx/compose/runtime/ComposerKt.traceEventEnd ()V
   L63
    GOTO L64
   L27
    LINENUMBER 45 L27
    ALOAD 7
    INVOKEINTERFACE androidx/compose/runtime/Composer.skipToGroupEnd ()V (itf)
   L64
    LINENUMBER 317 L64
    ALOAD 7
    INVOKEINTERFACE androidx/compose/runtime/Composer.endRestartGroup ()Landroidx/compose/runtime/ScopeUpdateScope; (itf)
    DUP
    IFNULL L65
    ALOAD 0
    ALOAD 1
    ALOAD 2
    ALOAD 3
    ALOAD 4
    ALOAD 5
    ALOAD 6
    ILOAD 8
    ILOAD 9
    INVOKEDYNAMIC invoke(Landroidx/navigation/NavHostController;Lkotlin/jvm/functions/Function0;Lkotlin/jvm/functions/Function1;Lkotlin/jvm/functions/Function0;Lkotlin/jvm/functions/Function0;Landroidx/compose/ui/Modifier;Ljava/lang/String;II)Lkotlin/jvm/functions/Function2; [
      // handle kind 0x6 : INVOKESTATIC
      java/lang/invoke/LambdaMetafactory.metafactory(Ljava/lang/invoke/MethodHandles$Lookup;Ljava/lang/String;Ljava/lang/invoke/MethodType;Ljava/lang/invoke/MethodType;Ljava/lang/invoke/MethodHandle;Ljava/lang/invoke/MethodType;)Ljava/lang/invoke/CallSite;
      // arguments:
      (Ljava/lang/Object;Ljava/lang/Object;)Ljava/lang/Object;, 
      // handle kind 0x6 : INVOKESTATIC
      com/fameafrica/afm2026/ui/navigation/NavGraphKt.FameNavGraph$lambda$163(Landroidx/navigation/NavHostController;Lkotlin/jvm/functions/Function0;Lkotlin/jvm/functions/Function1;Lkotlin/jvm/functions/Function0;Lkotlin/jvm/functions/Function0;Landroidx/compose/ui/Modifier;Ljava/lang/String;IILandroidx/compose/runtime/Composer;I)Lkotlin/Unit;, 
      (Landroidx/compose/runtime/Composer;Ljava/lang/Integer;)Lkotlin/Unit;
    ]
    INVOKEINTERFACE androidx/compose/runtime/ScopeUpdateScope.updateScope (Lkotlin/jvm/functions/Function2;)V (itf)
    GOTO L66
   L65
    POP
    NOP
   L66
    RETURN
   L67
    LOCALVARIABLE $i$a$-cache-NavGraphKt$FameNavGraph$1\3\321\0 I L53 L54 17
    LOCALVARIABLE value\2 Ljava/lang/Object; L56 L58 18
    LOCALVARIABLE $i$a$-let-ComposerKt$cache$1\2\319\1 I L50 L59 16
    LOCALVARIABLE it\1 Ljava/lang/Object; L49 L59 15
    LOCALVARIABLE $i$f$cache\1\59 I L48 L61 14
    LOCALVARIABLE $this$cache\1 Landroidx/compose/runtime/Composer; L47 L61 12
    LOCALVARIABLE invalid\1 Z L47 L61 13
    LOCALVARIABLE $dirty I L2 L67 10
    LOCALVARIABLE navController Landroidx/navigation/NavHostController; L0 L67 0
    LOCALVARIABLE onNewCareer Lkotlin/jvm/functions/Function0; L0 L67 1
    LOCALVARIABLE onContinue Lkotlin/jvm/functions/Function1; L0 L67 2
    LOCALVARIABLE onLoadGame Lkotlin/jvm/functions/Function0; L0 L67 3
    LOCALVARIABLE onSettings Lkotlin/jvm/functions/Function0; L0 L67 4
    LOCALVARIABLE modifier Landroidx/compose/ui/Modifier; L0 L67 5
    LOCALVARIABLE startDestination Ljava/lang/String; L0 L67 6
    LOCALVARIABLE $composer Landroidx/compose/runtime/Composer; L0 L67 7
    LOCALVARIABLE $changed I L0 L67 8
    MAXSTACK = 17
    MAXLOCALS = 30

File is unknown
The root cause java.lang.OutOfMemoryError was thrown at: org.jetbrains.org.objectweb.asm.tree.analysis.Frame.<init>(Frame.java:96)
	at org.jetbrains.kotlin.codegen.TransformationMethodVisitor.visitEnd(TransformationMethodVisitor.kt:89)
	at org.jetbrains.org.objectweb.asm.MethodVisitor.visitEnd(MethodVisitor.java:796)
	at org.jetbrains.org.objectweb.asm.tree.MethodNode.accept(MethodNode.java:770)
	at org.jetbrains.kotlin.backend.jvm.codegen.ClassCodegen.generateMethod(ClassCodegen.kt:469)
	at org.jetbrains.kotlin.backend.jvm.codegen.ClassCodegen.generate(ClassCodegen.kt:164)
	at org.jetbrains.kotlin.backend.jvm.JvmIrCodegenFactory.generateFile(JvmIrCodegenFactory.kt:419)
	at org.jetbrains.kotlin.backend.jvm.JvmIrCodegenFactory.invokeCodegen(JvmIrCodegenFactory.kt:388)
	at org.jetbrains.kotlin.cli.jvm.compiler.KotlinToJVMBytecodeCompiler.runCodegen$cli(KotlinToJVMBytecodeCompiler.kt:431)
	at org.jetbrains.kotlin.cli.pipeline.jvm.JvmBackendPipelinePhase.executePhase(JvmBackendPipelinePhase.kt:95)
	at org.jetbrains.kotlin.cli.pipeline.jvm.JvmBackendPipelinePhase.executePhase(JvmBackendPipelinePhase.kt:36)
	at org.jetbrains.kotlin.cli.pipeline.jvm.JvmBackendPipelinePhase.executePhase(JvmBackendPipelinePhase.kt:29)
	at org.jetbrains.kotlin.cli.pipeline.PipelinePhase.phaseBody(PipelinePhase.kt:68)
	at org.jetbrains.kotlin.cli.pipeline.PipelinePhase.phaseBody(PipelinePhase.kt:58)
	at org.jetbrains.kotlin.config.phaser.NamedCompilerPhase.invoke(CompilerPhase.kt:102)
	at org.jetbrains.kotlin.backend.common.phaser.CompositePhase.invoke(PhaseBuilders.kt:22)
	at org.jetbrains.kotlin.config.phaser.CompilerPhaseKt.invokeToplevel(CompilerPhase.kt:53)
	at org.jetbrains.kotlin.cli.pipeline.AbstractCliPipeline.runPhasedPipeline(AbstractCliPipeline.kt:109)
	at org.jetbrains.kotlin.cli.pipeline.AbstractCliPipeline.execute(AbstractCliPipeline.kt:68)
	at org.jetbrains.kotlin.cli.jvm.K2JVMCompiler.doExecutePhased(K2JVMCompiler.kt:78)
	at org.jetbrains.kotlin.cli.jvm.K2JVMCompiler.doExecutePhased(K2JVMCompiler.kt:44)
	at org.jetbrains.kotlin.cli.common.CLICompiler.execImpl(CLICompiler.kt:90)
	at org.jetbrains.kotlin.cli.common.CLICompiler.exec(CLICompiler.kt:352)
	at org.jetbrains.kotlin.incremental.IncrementalJvmCompilerRunnerBase.runCompiler(IncrementalJvmCompilerRunnerBase.kt:175)
	at org.jetbrains.kotlin.incremental.IncrementalJvmCompilerRunnerBase.runCompiler(IncrementalJvmCompilerRunnerBase.kt:38)
	at org.jetbrains.kotlin.incremental.IncrementalCompilerRunner.doCompile(IncrementalCompilerRunner.kt:504)
	at org.jetbrains.kotlin.incremental.IncrementalCompilerRunner.compileImpl(IncrementalCompilerRunner.kt:421)
	at org.jetbrains.kotlin.incremental.IncrementalCompilerRunner.compileNonIncrementally(IncrementalCompilerRunner.kt:306)
	at org.jetbrains.kotlin.incremental.IncrementalCompilerRunner.compile(IncrementalCompilerRunner.kt:133)
	at org.jetbrains.kotlin.daemon.CompileServiceImplBase.execIncrementalCompiler(CompileServiceImpl.kt:679)
	at org.jetbrains.kotlin.daemon.CompileServiceImplBase.access$execIncrementalCompiler(CompileServiceImpl.kt:93)
	at org.jetbrains.kotlin.daemon.CompileServiceImpl.compile(CompileServiceImpl.kt:1806)
	at java.base/jdk.internal.reflect.DirectMethodHandleAccessor.invoke(Unknown Source)
	at java.base/java.lang.reflect.Method.invoke(Unknown Source)
	at java.rmi/sun.rmi.server.UnicastServerRef.dispatch(Unknown Source)
	at java.rmi/sun.rmi.transport.Transport$1.run(Unknown Source)
	at java.rmi/sun.rmi.transport.Transport$1.run(Unknown Source)
	at java.base/java.security.AccessController.doPrivileged(Unknown Source)
	at java.rmi/sun.rmi.transport.Transport.serviceCall(Unknown Source)
	at java.rmi/sun.rmi.transport.tcp.TCPTransport.handleMessages(Unknown Source)
	at java.rmi/sun.rmi.transport.tcp.TCPTransport$ConnectionHandler.run0(Unknown Source)
	at java.rmi/sun.rmi.transport.tcp.TCPTransport$ConnectionHandler.lambda$run$0(Unknown Source)
	at java.base/java.security.AccessController.doPrivileged(Unknown Source)
	at java.rmi/sun.rmi.transport.tcp.TCPTransport$ConnectionHandler.run(Unknown Source)
	at java.base/java.util.concurrent.ThreadPoolExecutor.runWorker(Unknown Source)
	at java.base/java.util.concurrent.ThreadPoolExecutor$Worker.run(Unknown Source)
	at java.base/java.lang.Thread.run(Unknown Source)
Caused by: java.lang.OutOfMemoryError: GC overhead limit exceeded
	at org.jetbrains.org.objectweb.asm.tree.analysis.Frame.<init>(Frame.java:96)
	at org.jetbrains.kotlin.codegen.optimization.common.FastMethodAnalyzer._init_$lambda$0(FastMethodAnalyzer.kt:47)
	at org.jetbrains.kotlin.codegen.optimization.common.FastMethodAnalyzer$$Lambda/0x0000000100b284f0.invoke(Unknown Source)
	at org.jetbrains.kotlin.codegen.optimization.common.FastAnalyzer.fullMergeControlFlowEdge(FastAnalyzer.kt:233)
	at org.jetbrains.kotlin.codegen.optimization.common.FastAnalyzer.mergeControlFlowEdge(FastAnalyzer.kt:216)
	at org.jetbrains.kotlin.codegen.optimization.common.FastAnalyzer.processControlFlowEdge(FastAnalyzer.kt:208)
	at org.jetbrains.kotlin.codegen.optimization.common.FastAnalyzer.processControlFlowEdge$default(FastAnalyzer.kt:206)
	at org.jetbrains.kotlin.codegen.optimization.common.FastAnalyzer.visitOpInsn(FastAnalyzer.kt:292)
	at org.jetbrains.kotlin.codegen.optimization.common.FastAnalyzer.visitMeaningfulInstruction(FastAnalyzer.kt:281)
	at org.jetbrains.kotlin.codegen.optimization.common.FastAnalyzer.analyzeInstruction(FastAnalyzer.kt:113)
	at org.jetbrains.kotlin.codegen.optimization.common.FastAnalyzer.analyzeMainLoop(FastAnalyzer.kt:74)
	at org.jetbrains.kotlin.codegen.optimization.common.FastAnalyzer.analyze(FastAnalyzer.kt:53)
	at org.jetbrains.kotlin.codegen.optimization.boxing.PopBackwardPropagationTransformer$Transformer.transform(PopBackwardPropagationTransformer.kt:58)
	at org.jetbrains.kotlin.codegen.optimization.boxing.PopBackwardPropagationTransformer.transform(PopBackwardPropagationTransformer.kt:41)
	at org.jetbrains.kotlin.codegen.optimization.transformer.CompositeMethodTransformer.transform(CompositeMethodTransformer.kt:25)
	at org.jetbrains.kotlin.codegen.optimization.OptimizationMethodVisitor.performTransformations(OptimizationMethodVisitor.kt:74)
	at org.jetbrains.kotlin.codegen.TransformationMethodVisitor.visitEnd(TransformationMethodVisitor.kt:67)
	at org.jetbrains.org.objectweb.asm.MethodVisitor.visitEnd(MethodVisitor.java:796)
	at org.jetbrains.org.objectweb.asm.tree.MethodNode.accept(MethodNode.java:770)
	at org.jetbrains.kotlin.backend.jvm.codegen.ClassCodegen.generateMethod(ClassCodegen.kt:469)
	at org.jetbrains.kotlin.backend.jvm.codegen.ClassCodegen.generate(ClassCodegen.kt:164)
	at org.jetbrains.kotlin.backend.jvm.JvmIrCodegenFactory.generateFile(JvmIrCodegenFactory.kt:419)
	at org.jetbrains.kotlin.backend.jvm.JvmIrCodegenFactory.invokeCodegen(JvmIrCodegenFactory.kt:388)
	at org.jetbrains.kotlin.cli.jvm.compiler.KotlinToJVMBytecodeCompiler.runCodegen$cli(KotlinToJVMBytecodeCompiler.kt:431)
	at org.jetbrains.kotlin.cli.pipeline.jvm.JvmBackendPipelinePhase.executePhase(JvmBackendPipelinePhase.kt:95)
	at org.jetbrains.kotlin.cli.pipeline.jvm.JvmBackendPipelinePhase.executePhase(JvmBackendPipelinePhase.kt:36)
	at org.jetbrains.kotlin.cli.pipeline.jvm.JvmBackendPipelinePhase.executePhase(JvmBackendPipelinePhase.kt:29)
	at org.jetbrains.kotlin.cli.pipeline.PipelinePhase.phaseBody(PipelinePhase.kt:68)
	at org.jetbrains.kotlin.cli.pipeline.PipelinePhase.phaseBody(PipelinePhase.kt:58)
	at org.jetbrains.kotlin.config.phaser.NamedCompilerPhase.invoke(CompilerPhase.kt:102)
	at org.jetbrains.kotlin.backend.common.phaser.CompositePhase.invoke(PhaseBuilders.kt:22)
	at org.jetbrains.kotlin.config.phaser.CompilerPhaseKt.invokeToplevel(CompilerPhase.kt:53)


